autopager/__init__.py
autopager/__main__.py
autopager/autopager.crf
autopager/autopager.py
autopager/evaluate.py
autopager/htmlutils.py
autopager/limits.py
autopager/model.py
autopager/storage.py
autopager/utils.py
autopager-0.3-py3.8.egg-info/PKG-INFO
autopager-0.3-py3.8.egg-info/SOURCES.txt
autopager-0.3-py3.8.egg-info/dependency_links.txt
autopager-0.3-py3.8.egg-info/entry_points.txt
autopager-0.3-py3.8.egg-info/not-zip-safe
autopager-0.3-py3.8.egg-info/pbr.json
autopager-0.3-py3.8.egg-info/requires.txt
autopager-0.3-py3.8.egg-info/top_level.txt
autopager-0.3.1.dist-info/METADATA
autopager-0.3.1.dist-info/WHEEL
autopager-0.3.1.dist-info/entry_points.txt
autopager-0.3.1.dist-info/pbr.json
autopager-0.3.1.dist-info/top_level.txt
autopager-0.3.1.dist-info/RECORD
