Metadata-Version: 2.1
Name: autopager
Version: 0.3.1
Summary: Detect and classify pagination links on web pages
Home-page: https://github.com/TeamHG-Memex/autopager
Author: Mikhail Korobov
Author-email: kmike84@gmail.com
License: MIT license
Platform: UNKNOWN
Classifier: Development Status :: 3 - Alpha
Classifier: License :: OSI Approved :: MIT License
Classifier: Intended Audience :: Developers
Classifier: Operating System :: OS Independent
Classifier: Programming Language :: Python
Classifier: Programming Language :: Python :: 2
Classifier: Programming Language :: Python :: 2.7
Classifier: Programming Language :: Python :: 3
Classifier: Programming Language :: Python :: 3.3
Classifier: Programming Language :: Python :: 3.4
Classifier: Programming Language :: Python :: 3.5
Requires-Dist: six
Requires-Dist: w3lib (>=1.13.0)
Requires-Dist: parsel (>=1.0.1)
Requires-Dist: tldextract
Requires-Dist: docopt
Requires-Dist: sklearn-crfsuite (>=0.3.3)
